woohyunTest/BMI_module.py
woohyunTest/test1.py
woohyunTest/test2.py
woohyunTest-0.0.0.4.dist-info/METADATA
woohyunTest-0.0.0.4.dist-info/WHEEL
woohyunTest-0.0.0.4.dist-info/top_level.txt
woohyunTest-0.0.0.4.dist-info/RECORD
