Metadata-Version: 2.1
Name: woohyunTest
Version: 0.0.0.4
Summary: My First Test Package
Home-page: https://blog.naver.com/woohyun5838
Author: Woohyun Jeong
Author-email: woohyun583872@gmail.com
License: MIT
Platform: UNKNOWN
Requires-Python: >=3
